dots_ocr/__init__.py
dots_ocr/model/inference.py
dots_ocr/parser.py
dots_ocr/utils/__init__.py
dots_ocr/utils/consts.py
dots_ocr/utils/demo_utils/display.py
dots_ocr/utils/doc_utils.py
dots_ocr/utils/format_transformer.py
dots_ocr/utils/image_utils.py
dots_ocr/utils/layout_utils.py
dots_ocr/utils/output_cleaner.py
dots_ocr/utils/prompts.py
charlie_dots_ocr-0.0.6.dist-info/entry_points.txt
charlie_dots_ocr-0.0.6.dist-info/LICENSE
charlie_dots_ocr-0.0.6.dist-info/METADATA
charlie_dots_ocr-0.0.6.dist-info/NOTICE
charlie_dots_ocr-0.0.6.dist-info/WHEEL
charlie_dots_ocr-0.0.6.dist-info/RECORD
