Metadata-Version: 2.3
Name: charlie-dots-ocr
Version: 0.0.6
Summary: 0.0.6 remove accelerate. dots.ocr: Multilingual Document Layout Parsing in one Vision-Language Model
License: MIT
Keywords: ocr,document-parser,vision-language-model,layout-detection
Requires-Python: >=3.10,<3.13
Classifier: Development Status :: 4 - Beta
Classifier: Intended Audience :: Developers
Classifier: Intended Audience :: Science/Research
Classifier: License :: OSI Approved :: MIT License
Classifier: Programming Language :: Python :: 3
Classifier: Programming Language :: Python :: 3.10
Classifier: Programming Language :: Python :: 3.11
Classifier: Programming Language :: Python :: 3.12
Classifier: Topic :: Scientific/Engineering :: Artificial Intelligence
Classifier: Topic :: Text Processing :: General
Classifier: Topic :: Utilities
Requires-Dist: PyMuPDF (>=1.24.0,<2.0.0)
Requires-Dist: aiohttp (>=3.8.0,<4.0.0)
Requires-Dist: huggingface-hub (>=0.30.0,<1.0)
Requires-Dist: modelscope (>=1.18.0,<2.0.0)
Requires-Dist: openai (>=1.0.0,<2.0.0)
Requires-Dist: pillow (<12.0.0)
Requires-Dist: qwen-vl-utils
Requires-Dist: requests (>=2.30.0,<3.0.0)
Requires-Dist: tqdm (>=4.65.0,<5.0.0)
Requires-Dist: transformers (==4.51.3)
Project-URL: Bug Tracker, https://github.com/rednote-hilab/dots.ocr/issues
Project-URL: Documentation, https://github.com/rednote-hilab/dots.ocr
Project-URL: Homepage, https://github.com/rednote-hilab/dots.ocr
Project-URL: Repository, https://github.com/rednote-hilab/dots.ocr
